well_plate/__init__.py
well_plate/color_map.py
well_plate/config.py
well_plate/grid.py
well_plate/utils.py
well_plate/well_plate.py
well_plate-0.0.5.dist-info/LICENSE.txt
well_plate-0.0.5.dist-info/METADATA
well_plate-0.0.5.dist-info/WHEEL
well_plate-0.0.5.dist-info/top_level.txt
well_plate-0.0.5.dist-info/RECORD
