Metadata-Version: 2.1
Name: well_plate
Version: 0.0.5
Summary: Work with well plates!
Home-page: https://github.com/dylanwal/well_plate
Author: Dylan Walsh
License: BSD
Platform: any
Classifier: License :: OSI Approved :: BSD License
Classifier: Programming Language :: Python :: 3
Classifier: Programming Language :: Python :: 3 :: Only
Classifier: Programming Language :: Python :: 3.9
Requires-Python: >=3.9
License-File: LICENSE.txt
Requires-Dist: numpy >=1.21.5
Requires-Dist: pandas >=1.4.2
Requires-Dist: plotly >=5.6.0
